Graphite/__init__.py
graphiteinterv2-0.3.5.dist-info/METADATA
graphiteinterv2-0.3.5.dist-info/WHEEL
graphiteinterv2-0.3.5.dist-info/top_level.txt
graphiteinterv2-0.3.5.dist-info/RECORD
