Metadata-Version: 2.1
Name: graphiteinterv2
Version: 0.3.5
Summary: A simple GUI framework with tkinter for creating interactive interfaces.
Author: Leonardo
Author-email: leo_nery@hotmail.com.br
Classifier: Programming Language :: Python :: 3
Classifier: License :: OSI Approved :: MIT License
Classifier: Operating System :: OS Independent
Requires-Python: >=3.6
Requires-Dist: Pillow
